aivoice_python/__init__.py
aivoice_python/aivoice_control.py
aivoice_python-0.1.5.dist-info/licenses/LICENSE
aivoice_python-0.1.5.dist-info/METADATA
aivoice_python-0.1.5.dist-info/WHEEL
aivoice_python-0.1.5.dist-info/top_level.txt
aivoice_python-0.1.5.dist-info/RECORD
