Metadata-Version: 2.4
Name: aivoice-python
Version: 0.1.5
Summary: A Python wrapper for A.I.VOICE Editor API
Author-email: yupix <yupi0982@outlook.jp>
License: MIT
Project-URL: Homepage, https://github.com/yupix/aivoice-python
Project-URL: Repository, https://github.com/yupix/aivoice-python
Project-URL: Documentation, https://github.com/yupix/aivoice-python#readme
Project-URL: Bug Tracker, https://github.com/yupix/aivoice-python/issues
Keywords: aivoice,tts,text-to-speech,voice-synthesis
Classifier: Development Status :: 4 - Beta
Classifier: Intended Audience :: Developers
Classifier: License :: OSI Approved :: MIT License
Classifier: Operating System :: Microsoft :: Windows
Classifier: Programming Language :: Python :: 3
Classifier: Programming Language :: Python :: 3.8
Classifier: Programming Language :: Python :: 3.9
Classifier: Programming Language :: Python :: 3.10
Classifier: Programming Language :: Python :: 3.11
Classifier: Programming Language :: Python :: 3.12
Classifier: Topic :: Multimedia :: Sound/Audio :: Speech
Classifier: Topic :: Software Development :: Libraries :: Python Modules
Requires-Python: >=3.8
License-File: LICENSE
Requires-Dist: pythonnet>=3.0.0
Requires-Dist: typing-extensions>=4.0.0; python_version < "3.11"
Provides-Extra: dev
Requires-Dist: pytest>=6.0; extra == "dev"
Requires-Dist: black; extra == "dev"
Requires-Dist: flake8; extra == "dev"
Requires-Dist: mypy; extra == "dev"
Dynamic: license-file
